mbfxml2ex/__init__.py
mbfxml2ex/app.py
mbfxml2ex/classes.py
mbfxml2ex/conversions.py
mbfxml2ex/definitions.py
mbfxml2ex/exceptions.py
mbfxml2ex/parsers.py
mbfxml2ex/templates.py
mbfxml2ex/utilities.py
mbfxml2ex/zinc.py
mbfxml2ex-0.8.4.dist-info/licenses/LICENSE
mbfxml2ex-0.8.4.dist-info/METADATA
mbfxml2ex-0.8.4.dist-info/WHEEL
mbfxml2ex-0.8.4.dist-info/entry_points.txt
mbfxml2ex-0.8.4.dist-info/top_level.txt
mbfxml2ex-0.8.4.dist-info/RECORD
