Metadata-Version: 2.4
Name: mbfxml2ex
Version: 0.8.4
Summary: Python library for generating Ex format model descriptions from MBF XML formatted data.
Author-email: Hugh Sorby <h.sorby@auckland.ac.nz>
License-Expression: Apache-2.0
Keywords: Medical,Physiology,Mesh,Finite Element,Convert,Neuroscience
Classifier: Programming Language :: Python :: 3
Classifier: Operating System :: OS Independent
Classifier: Topic :: Scientific/Engineering :: Medical Science Apps.
Requires-Python: >=3.8
License-File: LICENSE
Requires-Dist: cmlibs.utils>=0.6
Requires-Dist: cmlibs.zinc>=4.1
Provides-Extra: test
Requires-Dist: coverage; extra == "test"
Requires-Dist: packaging; extra == "test"
Requires-Dist: pytest; extra == "test"
Dynamic: license-file
